LICENCE
README.md
setup.py
WeavexPy/__init__.py
WeavexPy/_messagebox_.py
WeavexPy/css.py
WeavexPy/desktop.py
WeavexPy/ehtml.py
WeavexPy/obj.py
WeavexPy/script.py
WeavexPy/server.py
WeavexPy/style.py
WeavexPy.egg-info/PKG-INFO
WeavexPy.egg-info/SOURCES.txt
WeavexPy.egg-info/dependency_links.txt
WeavexPy.egg-info/requires.txt
WeavexPy.egg-info/top_level.txt
weavexpy.egg-info/PKG-INFO
weavexpy.egg-info/SOURCES.txt
weavexpy.egg-info/dependency_links.txt
weavexpy.egg-info/requires.txt
weavexpy.egg-info/top_level.txt