Metadata-Version: 2.4
Name: weavexpy
Version: 0.1.2
Summary: WeavexPy - 0.1.2 - beta
Author: João Victor
Author-email: joaovictor.dev.git@gmail.com
License: MIT License
Keywords: WeavexPy
License-File: LICENCE
Requires-Dist: pywebview
Requires-Dist: flask
Requires-Dist: flask_cors
Dynamic: author
Dynamic: author-email
Dynamic: description
Dynamic: description-content-type
Dynamic: keywords
Dynamic: license
Dynamic: license-file
Dynamic: requires-dist
Dynamic: summary
